liftpose/main.py
liftpose/plot.py
liftpose/postprocess.py
liftpose/preprocess.py
liftpose/vision_3d.py
liftpose/lifter/augmentation.py
liftpose/lifter/data_loader_fun.py
liftpose/lifter/lift.py
liftpose/lifter/log.py
liftpose/lifter/model.py
liftpose/lifter/opt.py
liftpose/lifter/test.py
liftpose/lifter/train.py
liftpose/lifter/utils.py
liftpose-0.22.dist-info/LICENSE
liftpose-0.22.dist-info/METADATA
liftpose-0.22.dist-info/WHEEL
liftpose-0.22.dist-info/top_level.txt
liftpose-0.22.dist-info/RECORD
