Metadata-Version: 2.1
Name: liftpose
Version: 0.22
Summary: Monocular 3D pose Estimation on Laboratory Animals
Home-page: https://github.com/NeLy-EPFL/LiftPose3D
Author: Adam Gosztolai & Semih Gunel
License: UNKNOWN
Platform: UNKNOWN
